onnxscript/__init__.py
onnxscript/converter.py
onnxscript/evaluator.py
onnxscript/irbuilder.py
onnxscript/main.py
onnxscript/onnx_types.py
onnxscript/py.typed
onnxscript/sourceinfo.py
onnxscript/tensor.py
onnxscript/type_annotation.py
onnxscript/values.py
onnxscript/_framework_apis/__init__.py
onnxscript/_framework_apis/torch_2_5.py
onnxscript/_framework_apis/torch_2_6.py
onnxscript/_framework_apis/torch_2_7.py
onnxscript/_framework_apis/torch_2_8.py
onnxscript/_framework_apis/torch_2_9.py
onnxscript/_internal/__init__.py
onnxscript/_internal/analysis.py
onnxscript/_internal/ast_utils.py
onnxscript/_internal/autocast.py
onnxscript/_internal/deprecation.py
onnxscript/_internal/param_manipulation.py
onnxscript/_internal/utils.py
onnxscript/_internal/version_utils.py
onnxscript/_thirdparty/asciichartpy.py
onnxscript/backend/__init__.py
onnxscript/backend/onnx_backend.py
onnxscript/backend/onnx_export.py
onnxscript/function_libs/tools/torch_lib/deduce_type_constraints.py
onnxscript/function_libs/tools/torch_lib/generate_aten_signatures.py
onnxscript/function_libs/tools/torch_lib/generate_prims_signatures.py
onnxscript/function_libs/torch_lib/__init__.py
onnxscript/function_libs/torch_lib/_constants.py
onnxscript/function_libs/torch_lib/_flags.py
onnxscript/function_libs/torch_lib/registration.py
onnxscript/function_libs/torch_lib/tensor_typing.py
onnxscript/function_libs/torch_lib/graph_building/__init__.py
onnxscript/function_libs/torch_lib/ops/__init__.py
onnxscript/function_libs/torch_lib/ops/common.py
onnxscript/function_libs/torch_lib/ops/core.py
onnxscript/function_libs/torch_lib/ops/fft.py
onnxscript/function_libs/torch_lib/ops/linalg.py
onnxscript/function_libs/torch_lib/ops/nested.py
onnxscript/function_libs/torch_lib/ops/nn.py
onnxscript/function_libs/torch_lib/ops/prims.py
onnxscript/function_libs/torch_lib/ops/quantized_decomposed.py
onnxscript/function_libs/torch_lib/ops/sparse.py
onnxscript/function_libs/torch_lib/ops/special.py
onnxscript-0.5.4.dist-info/licenses/LICENSE
onnxscript-0.5.4.dist-info/METADATA
onnxscript-0.5.4.dist-info/WHEEL
onnxscript-0.5.4.dist-info/top_level.txt
onnxscript-0.5.4.dist-info/RECORD
