Metadata-Version: 2.4
Name: onnxscript
Version: 0.5.4
Summary: Naturally author ONNX functions and models using a subset of Python
Author-email: Microsoft Corporation <onnx@microsoft.com>
License: MIT License
Project-URL: Homepage, https://microsoft.github.io/onnxscript/
Project-URL: Repository, https://github.com/microsoft/onnxscript
Classifier: Development Status :: 4 - Beta
Classifier: Environment :: Console
Classifier: Intended Audience :: Developers
Classifier: Operating System :: POSIX
Classifier: Operating System :: MacOS :: MacOS X
Classifier: Operating System :: Microsoft :: Windows
Classifier: Programming Language :: Python :: 3.9
Classifier: Programming Language :: Python :: 3.10
Classifier: Programming Language :: Python :: 3.11
Classifier: Programming Language :: Python :: 3.12
Classifier: Programming Language :: Python :: 3.13
Classifier: License :: OSI Approved :: MIT License
Requires-Python: >=3.9
License-File: LICENSE
Requires-Dist: ml_dtypes
Requires-Dist: numpy
Requires-Dist: onnx_ir<2,>=0.1.10
Requires-Dist: onnx>=1.16
Requires-Dist: packaging
Requires-Dist: typing_extensions>=4.10
Dynamic: license-file
Dynamic: project-url
